{
  "namespace": "cognovamx",
  "name": "mx-run",
  "version": "1.0",
  "description": "Universal cog executor — looks up any cog by name, lists its actions, and dispatches execution by runtime",
  "author": "Tom Cranstoun and Maxine",
  "maintainer": "mx.machine.experience@gmail.com",
  "license": "proprietary",
  "status": "draft",
  "category": "mx-core",
  "tags": [
    "executor",
    "runtime",
    "dispatcher",
    "cli",
    "cog",
    "mx-os"
  ],
  "type": "action-doc",
  "compliance_level": 2,
  "created": "2026-02-11",
  "modified": "2026-02-11",
  "source_path": "scripts/cogs/mx-run.cog.md",
  "source_url": "https://github.com/Digital-Domain-Technologies-Ltd/MX-hub/blob/main/scripts/cogs/mx-run.cog.md",
  "content_url": "/reginald/cogs/cognovamx/mx-run/content.md"
}