{
  "namespace": "cog-nova-mx",
  "name": "block-naming-decision",
  "version": "1.0",
  "description": "NDR #1: The word 'block' risks confusion with blockchain. Propose alternatives for advisory board review.",
  "author": "Tom Cranstoun and Maxine",
  "maintainer": "tom.cranstoun@gmail.com",
  "license": "MIT",
  "status": "proposed",
  "category": "naming",
  "tags": [
    "ndr",
    "naming",
    "blocks",
    "terminology",
    "advisory-board"
  ],
  "type": "info-doc",
  "compliance_level": 2,
  "created": "2026-02-13",
  "modified": "2026-02-28",
  "source_path": "mx-canon/mx-the-gathering/naming-decisions/ndr-01-block-naming.cog.md",
  "source_url": "https://github.com/Digital-Domain-Technologies-Ltd/MX-hub/blob/main/mx-canon/mx-the-gathering/naming-decisions/ndr-01-block-naming.cog.md",
  "content_url": "/reginald/cogs/cog-nova-mx/block-naming-decision/content.md"
}